mcp_postgres_semantic/__init__.py
mcp_postgres_semantic/server.py
mcp_postgres_semantic-1.0.0.dist-info/METADATA
mcp_postgres_semantic-1.0.0.dist-info/WHEEL
mcp_postgres_semantic-1.0.0.dist-info/entry_points.txt
mcp_postgres_semantic-1.0.0.dist-info/RECORD
