Metadata-Version: 2.4
Name: mcp-postgres-semantic
Version: 1.0.0
Summary: MCP server for PostgreSQL with semantic search via pgvector and OpenAI embeddings
Author-email: Your Name <your.email@example.com>
Requires-Python: >=3.10
Requires-Dist: mcp>=0.9.0
Requires-Dist: openai>=1.12.0
Requires-Dist: psycopg2-binary>=2.9.9
Provides-Extra: dev
Requires-Dist: black>=23.0.0; extra == 'dev'
Requires-Dist: mypy>=1.0.0; extra == 'dev'
Requires-Dist: pytest>=7.4.0; extra == 'dev'
